sqlitewithoutsql/__init__.py
sqlitewithoutsql/database.py
sqlitewithoutsql/sqltype.py
sqlitewithoutsql-1.1.0.dist-info/LICENSE
sqlitewithoutsql-1.1.0.dist-info/METADATA
sqlitewithoutsql-1.1.0.dist-info/WHEEL
sqlitewithoutsql-1.1.0.dist-info/top_level.txt
sqlitewithoutsql-1.1.0.dist-info/RECORD
