Metadata-Version: 2.1
Name: sqlitewithoutsql
Version: 1.1.0
Summary: My first module for using sqlite without sql
Home-page: https://github.com/evryz4/sqlitewithoutsql
Author: evryz4
Author-email: evryhvh@gmail.com
License-File: LICENSE
